evofabric/__init__.py
evofabric/logger.py
evofabric/app/__init__.py
evofabric/app/kernel_evolve/__init__.py
evofabric/app/kernel_evolve/core/__init__.py
evofabric/app/kernel_evolve/core/controller.py
evofabric/app/kernel_evolve/core/llm_config.py
evofabric/app/kernel_evolve/evaluator/__init__.py
evofabric/app/kernel_evolve/evaluator/base_evaluator.py
evofabric/app/kernel_evolve/evaluator/evaluation_result.py
evofabric/app/kernel_evolve/evaluator/kernel_eval.py
evofabric/app/kernel_evolve/prompt/__init__.py
evofabric/app/kernel_evolve/prompt/sample_prompt.py
evofabric/app/sop2workflow/__init__.py
evofabric/app/sop2workflow/_base.py
evofabric/app/sop2workflow/_generator.py
evofabric/app/sop2workflow/_prompt.py
evofabric/core/__init__.py
evofabric/core/agent/__init__.py
evofabric/core/agent/_agent.py
evofabric/core/agent/_user_node.py
evofabric/core/clients/__init__.py
evofabric/core/clients/_base.py
evofabric/core/clients/_openai.py
evofabric/core/clients/_pangu.py
evofabric/core/clients/_rag_clients.py
evofabric/core/factory/__init__.py
evofabric/core/factory/_factory.py
evofabric/core/factory/_function.py
evofabric/core/factory/_state.py
evofabric/core/factory/_utils.py
evofabric/core/graph/__init__.py
evofabric/core/graph/_edge.py
evofabric/core/graph/_engine.py
evofabric/core/graph/_engine_debugger.py
evofabric/core/graph/_graph.py
evofabric/core/graph/_node.py
evofabric/core/graph/_plot.py
evofabric/core/graph/_state.py
evofabric/core/graph/_state_update.py
evofabric/core/graph/_streaming.py
evofabric/core/graph/_utils.py
evofabric/core/mem/__init__.py
evofabric/core/mem/_base_mem.py
evofabric/core/mem/_chat_mem.py
evofabric/core/mem/_cognitive_mem.py
evofabric/core/mem/_default_mem_prompt_en.py
evofabric/core/mem/_default_mem_prompt_zh.py
evofabric/core/mem/_retrieval_mem.py
evofabric/core/mem/_task_mem.py
evofabric/core/multi_agent/__init__.py
evofabric/core/multi_agent/_swarm.py
evofabric/core/tool/__init__.py
evofabric/core/tool/_base_tool.py
evofabric-0.1.3.dist-info/licenses/LICENSE
evofabric-0.1.3.dist-info/METADATA
evofabric-0.1.3.dist-info/WHEEL
evofabric-0.1.3.dist-info/top_level.txt
evofabric-0.1.3.dist-info/RECORD
