Metadata-Version: 2.4
Name: evofabric
Version: 0.1.3
Summary: An Open, Evolvable Agent Framework for Creative Intelligence System
Project-URL: Homepage, https://github.com/huawei-noah/noah-research/tree/master/EvoFabric
Classifier: Programming Language :: Python :: 3
Classifier: License :: OSI Approved :: MIT License
Classifier: Operating System :: OS Independent
Requires-Python: >=3.11
License-File: LICENSE
Requires-Dist: pip
Requires-Dist: build
Requires-Dist: pydantic
Requires-Dist: setuptools
Requires-Dist: loguru
Requires-Dist: httpx
Requires-Dist: openai
Requires-Dist: pydantic_core
Requires-Dist: contextvars
Requires-Dist: numpy
Requires-Dist: mcp>=1.16.0
Requires-Dist: docstring_parser
Requires-Dist: chromadb>=1.1.0
Requires-Dist: fastmcp>=2.12.2
Requires-Dist: docker>=7.1.0
Requires-Dist: openai>=1.0.0
Requires-Dist: pyyaml>=6.0
Requires-Dist: numpy>=1.22.0
Requires-Dist: tqdm>=4.64.0
Requires-Dist: flask
Requires-Dist: cloudpickle
Dynamic: license-file
